README.rst
setup.py
tfix/__init__.py
tfix/fix.py
tfix/gen.py
tfix/install.py
tfix/main.py
tfix/root.py
tfix/include/def.h
tfix/include/dev.h
tfix/lib/patch.c
tigerfix.egg-info/PKG-INFO
tigerfix.egg-info/SOURCES.txt
tigerfix.egg-info/dependency_links.txt
tigerfix.egg-info/entry_points.txt
tigerfix.egg-info/requires.txt
tigerfix.egg-info/top_level.txt