Metadata-Version: 1.0
Name: tigerfix
Version: 0.1.3
Summary: A hot fix tool for compiled languages such as c and c++.
Home-page: https://github.com/NiceKingWei/tigerfix
Author: UNKNOWN
Author-email: nicekingwei@foxmail.com
License: GPL-3.0
Keywords: hotfix c cpp
Platform: UNKNOWN
